pygridgain_dbapi/__init__.py
pygridgain_dbapi/_pygridgain_dbapi_extension.cpython-313-x86_64-linux-gnu.so
pygridgain_dbapi/_version.txt
pygridgain_dbapi/native_type_code.py
tests/__init__.py
tests/conftest.py
tests/test_connect.py
tests/test_dbapi_compliance.py
tests/test_errors.py
tests/test_execute.py
tests/test_executemany.py
tests/test_fetch_constants.py
tests/test_fetch_parameters.py
tests/test_fetch_table.py
tests/test_ssl.py
tests/test_transactions.py
tests/util.py
tests/ssl/ca.pem
tests/ssl/client.pem
tests/ssl/client_unknown.pem
pygridgain_dbapi-9.1.16.dist-info/METADATA
pygridgain_dbapi-9.1.16.dist-info/WHEEL
pygridgain_dbapi-9.1.16.dist-info/top_level.txt
pygridgain_dbapi-9.1.16.dist-info/RECORD
pygridgain_dbapi-9.1.16.dist-info/licenses/LICENSE
pygridgain_dbapi-9.1.16.dist-info/licenses/NOTICE
